rotating_logger/__init__.py
rotating_logger/rotatinglogger.py
rotating_logger/singleton.py
rotating_logger-0.1.1.dist-info/LICENSE
rotating_logger-0.1.1.dist-info/METADATA
rotating_logger-0.1.1.dist-info/WHEEL
rotating_logger-0.1.1.dist-info/top_level.txt
rotating_logger-0.1.1.dist-info/RECORD
