Metadata-Version: 2.1
Name: rotating_logger
Version: 0.1.1
Summary: A singleton rotating logger
Home-page: https://github.com/romainmrad/rotating_logger.git
Author: Romain MRAD
Author-email: Romain Mrad <romain.mrad@gmail.com>
Project-URL: Homepage, https://github.com/romainmrad/rotating_logger.git
Classifier: Programming Language :: Python :: 3
Classifier: License :: OSI Approved :: MIT License
Classifier: Operating System :: OS Independent
Requires-Python: >=3.8
License-File: LICENSE
